actionlib_msgs/msg/GoalID.py
actionlib_msgs/msg/GoalStatus.py
actionlib_msgs/msg/GoalStatusArray.py
actionlib_msgs/msg/__init__.py
builtin_interfaces/msg/Duration.py
builtin_interfaces/msg/Time.py
builtin_interfaces/msg/__init__.py
common_interfaces/__init__.py
common_interfaces/base_types.py
common_interfaces/build.py
common_interfaces/constants.py
common_interfaces/interface.py
common_interfaces/package.py
common_interfaces/parser.py
diagnostic_msgs/msg/DiagnosticArray.py
diagnostic_msgs/msg/DiagnosticStatus.py
diagnostic_msgs/msg/KeyValue.py
diagnostic_msgs/msg/__init__.py
geometry_msgs/msg/Accel.py
geometry_msgs/msg/AccelStamped.py
geometry_msgs/msg/AccelWithCovariance.py
geometry_msgs/msg/AccelWithCovarianceStamped.py
geometry_msgs/msg/Inertia.py
geometry_msgs/msg/InertiaStamped.py
geometry_msgs/msg/Point.py
geometry_msgs/msg/Point32.py
geometry_msgs/msg/PointStamped.py
geometry_msgs/msg/Polygon.py
geometry_msgs/msg/PolygonStamped.py
geometry_msgs/msg/Pose.py
geometry_msgs/msg/Pose2D.py
geometry_msgs/msg/PoseArray.py
geometry_msgs/msg/PoseStamped.py
geometry_msgs/msg/PoseWithCovariance.py
geometry_msgs/msg/PoseWithCovarianceStamped.py
geometry_msgs/msg/Quaternion.py
geometry_msgs/msg/QuaternionStamped.py
geometry_msgs/msg/Transform.py
geometry_msgs/msg/TransformStamped.py
geometry_msgs/msg/Twist.py
geometry_msgs/msg/TwistStamped.py
geometry_msgs/msg/TwistWithCovariance.py
geometry_msgs/msg/TwistWithCovarianceStamped.py
geometry_msgs/msg/Vector3.py
geometry_msgs/msg/Vector3Stamped.py
geometry_msgs/msg/VelocityStamped.py
geometry_msgs/msg/Wrench.py
geometry_msgs/msg/WrenchStamped.py
geometry_msgs/msg/__init__.py
nav_msgs/msg/GridCells.py
nav_msgs/msg/MapMetaData.py
nav_msgs/msg/OccupancyGrid.py
nav_msgs/msg/Odometry.py
nav_msgs/msg/Path.py
nav_msgs/msg/__init__.py
sensor_msgs/msg/BatteryState.py
sensor_msgs/msg/CameraInfo.py
sensor_msgs/msg/ChannelFloat32.py
sensor_msgs/msg/CompressedImage.py
sensor_msgs/msg/FluidPressure.py
sensor_msgs/msg/Illuminance.py
common_interfaces_intellisense-0.1.0.dist-info/LICENSE
common_interfaces_intellisense-0.1.0.dist-info/METADATA
common_interfaces_intellisense-0.1.0.dist-info/WHEEL
common_interfaces_intellisense-0.1.0.dist-info/top_level.txt
common_interfaces_intellisense-0.1.0.dist-info/RECORD
