Metadata-Version: 2.1
Name: common-interfaces-intellisense
Version: 0.1.0
Summary: Get intellisense for ROS 2 interfaces
Author-email: offish <overutilization@gmail.com>
Project-URL: Homepage, https://github.com/offish/common-interfaces-intellisense
Project-URL: Bug Tracker, https://github.com/offish/common-interfaces-intellisense/issues
Classifier: Programming Language :: Python :: 3
Classifier: License :: OSI Approved :: MIT License
Classifier: Operating System :: OS Independent
Requires-Python: >=3.10
License-File: LICENSE
